duelboard/__init__.py
duelboard/analyzers.py
duelboard/models.py
duelboard/py.typed
duelboard/types.py
duelboard/utils.py
duelboard/visualization.py
duelboard/calculators/__init__.py
duelboard/calculators/base.py
duelboard/calculators/bootstrap.py
duelboard/calculators/mle.py
duelboard-0.1.0.dist-info/METADATA
duelboard-0.1.0.dist-info/WHEEL
duelboard-0.1.0.dist-info/RECORD
