Metadata-Version: 2.4
Name: duelboard
Version: 0.1.0
Summary: A high-performance Elo rating calculation library for tournaments and competitions
Author-email: Jannchie <jannchie@gmail.com>
Requires-Python: >=3.13
Requires-Dist: kaleido>=1.0.0
Requires-Dist: numpy>=1.24.0
Requires-Dist: pandas>=2.0.0
Requires-Dist: pytest-cov>=6.2.1
Requires-Dist: pytest>=8.4.1
Requires-Dist: scikit-learn>=1.3.0
Requires-Dist: tqdm>=4.65.0
Provides-Extra: dev
Requires-Dist: pytest-cov>=4.1.0; extra == 'dev'
Requires-Dist: pytest>=7.4.0; extra == 'dev'
Requires-Dist: ruff>=0.0.287; extra == 'dev'
Provides-Extra: visualization
Requires-Dist: plotly>=5.15.0; extra == 'visualization'
